cds_sorenson/__init__.py
cds_sorenson/api.py
cds_sorenson/config.py
cds_sorenson/error.py
cds_sorenson/ext.py
cds_sorenson/proxies.py
cds_sorenson/utils.py
cds_sorenson/version.py
cds_sorenson-0.1.8.dist-info/AUTHORS.rst
cds_sorenson-0.1.8.dist-info/LICENSE
cds_sorenson-0.1.8.dist-info/METADATA
cds_sorenson-0.1.8.dist-info/WHEEL
cds_sorenson-0.1.8.dist-info/entry_points.txt
cds_sorenson-0.1.8.dist-info/top_level.txt
cds_sorenson-0.1.8.dist-info/RECORD
